heat_tempest_plugin/__init__.py
heat_tempest_plugin/config.py
heat_tempest_plugin/plugin.py
heat_tempest_plugin/common/__init__.py
heat_tempest_plugin/common/exceptions.py
heat_tempest_plugin/common/remote_client.py
heat_tempest_plugin/common/test.py
heat_tempest_plugin/services/__init__.py
heat_tempest_plugin/services/clients.py
heat_tempest_plugin/tests/__init__.py
heat_tempest_plugin/tests/api/__init__.py
heat_tempest_plugin/tests/api/fixtures.py
heat_tempest_plugin/tests/api/test_heat_api.py
heat_tempest_plugin/tests/api/gabbits/environments.yaml
heat_tempest_plugin/tests/api/gabbits/resources.yaml
heat_tempest_plugin/tests/api/gabbits/resourcetypes.yaml
heat_tempest_plugin/tests/api/gabbits/softwareconfig.yaml
heat_tempest_plugin/tests/api/gabbits/stacks.yaml
heat_tempest_plugin/tests/api/gabbits/templates.yaml
heat_tempest_plugin/tests/functional/__init__.py
heat_tempest_plugin/tests/functional/functional_base.py
heat_tempest_plugin/tests/functional/test_create_update_neutron_port.py
heat_tempest_plugin/tests/functional/test_create_update_neutron_subnet.py
heat_tempest_plugin/tests/functional/test_create_update_neutron_trunk.py
heat_tempest_plugin/tests/functional/test_encrypted_parameter.py
heat_tempest_plugin/tests/functional/test_encryption_vol_type.py
heat_tempest_plugin/tests/functional/test_event_sinks.py
heat_tempest_plugin/tests/functional/test_external_ref.py
heat_tempest_plugin/tests/functional/test_extra_route_set.py
heat_tempest_plugin/tests/functional/test_hooks.py
heat_tempest_plugin/tests/functional/test_nova_server_networks.py
heat_tempest_plugin/tests/functional/test_os_wait_condition.py
heat_tempest_plugin/tests/functional/test_preview.py
heat_tempest_plugin/tests/functional/test_remote_stack.py
heat_tempest_plugin/tests/functional/test_resources_list.py
heat_tempest_plugin/tests/functional/test_software_config.py
heat_tempest_plugin/tests/functional/test_stack_events.py
heat_tempest_plugin/tests/functional/test_stack_outputs.py
heat_tempest_plugin-2.6.0.dist-info/AUTHORS
heat_tempest_plugin-2.6.0.dist-info/LICENSE
heat_tempest_plugin-2.6.0.dist-info/METADATA
heat_tempest_plugin-2.6.0.dist-info/WHEEL
heat_tempest_plugin-2.6.0.dist-info/entry_points.txt
heat_tempest_plugin-2.6.0.dist-info/pbr.json
heat_tempest_plugin-2.6.0.dist-info/top_level.txt
heat_tempest_plugin-2.6.0.dist-info/RECORD
